README.md
setup.cfg
setup.py
mope/__init__.py
mope/_binom.c
mope/_interp.c
mope/_likes.c
mope/_poisson_binom.c
mope/_transition.c
mope/_util.c
mope/_wf.c
mope/acceptance.py
mope/add_detection_noise.py
mope/ages.py
mope/ascertainment.py
mope/cli.py
mope/count_heteroplasmies.py
mope/data.py
mope/download_transitions.py
mope/generate_transitions.py
mope/generate_transitions_util.py
mope/get_ages_from_sims.py
mope/inference.py
mope/initialguess.py
mope/likelihoods.py
mope/make_bottleneck_matrices.py
mope/make_figures.py
mope/make_transition_matrices.py
mope/mcmc.py
mope/newick.py
mope/params.py
mope/pso.py
mope/simulate.py
mope/simulate_msprime.py
mope/transition_data_bottleneck.py
mope/transition_data_mut.py
mope/util.py
mope.egg-info/PKG-INFO
mope.egg-info/SOURCES.txt
mope.egg-info/dependency_links.txt
mope.egg-info/entry_points.txt
mope.egg-info/requires.txt
mope.egg-info/top_level.txt