Metadata-Version: 1.2
Name: mope
Version: 0.3.1
Summary: Molecular ontogenetic phylogeny estimation
Home-page: UNKNOWN
Author: Peter Wilton
Author-email: pwilton@berkeley.edu
License: GPLv3
Platform: UNKNOWN
Requires-Python: >=2.7
